{
  "0": {
    "0": 830,
    "0": 5010
  },
  "1": {
    "0": 236,
    "0": 4336
  },
  "2": {
    "0": 236,
    "0": 4436
  },
  "3": {
    "0": 164,
    "0": 4200
  },
  "4": {
    "0": 158,
    "0": 4194
  },
  "5": {
    "0": 164,
    "0": 4200
  },
  "6": {
    "0": 262,
    "0": 4300
  },
  "7": {
    "0": 160,
    "0": 4230
  },
  "8": {
    "0": 168,
    "0": 4200
  },
  "9": {
    "0": 162,
    "0": 4204
  },
  "10": {
    "0": 248,
    "0": 4268
  },
  "11": {
    "0": 168,
    "0": 4182
  },
  "12": {
    "0": 156,
    "0": 4360
  },
  "13": {
    "0": 150,
    "0": 4180
  },
  "14": {
    "0": 156,
    "0": 4180
  },
  "15": {
    "0": 158,
    "0": 4182
  },
  "16": {
    "0": 154,
    "0": 4180
  },
  "17": {
    "0": 158,
    "0": 4184
  },
  "18": {
    "0": 268,
    "0": 4300
  },
  "19": {
    "0": 154,
    "0": 4180
  },
  "20": {
    "0": 154,
    "0": 4184
  },
  "21": {
    "0": 154,
    "0": 4178
  },
  "22": {
    "0": 152,
    "0": 4178
  },
  "23": {
    "0": 212,
    "1": 5416
  },
  "24": {
    "0": 696,
    "1": 2458
  },
  "25": {
    "0": 536,
    "2": 4664
  },
  "26": {
    "0": 508,
    "2": 1320
  },
  "27": {
    "0": 474,
    "2": 2570
  },
  "28": {
    "0": 564,
    "1": 2362
  },
  "29": {
    "0": 678,
    "2": 1386
  },
  "30": {
    "0": 502,
    "2": 1126
  },
  "31": {
    "0": 580,
    "2": 2302
  },
  "32": {
    "0": 510,
    "2": 1110
  },
  "33": {
    "0": 510,
    "2": 1052
  },
  "34": {
    "0": 510,
    "1": 2968
  },
  "35": {
    "0": 518,
    "2": 3486
  },
  "36": {
    "0": 518,
    "2": 4580
  },
  "37": {
    "0": 502,
    "2": 1882
  },
  "38": {
    "0": 514,
    "1": 1464
  },
  "39": {
    "0": 520,
    "1": 1384
  },
  "40": {
    "0": 514,
    "2": 1850
  },
  "41": {
    "0": 534,
    "1": 3586
  },
  "42": {
    "0": 522,
    "2": 3832
  },
  "43": {
    "0": 634,
    "0": 4690
  },
  "44": {
    "0": 316,
    "3": 3712
  },
  "45": {
    "0": 604,
    "3": 2460
  },
  "46": {
    "0": 588,
    "2": 1952
  },
  "47": {
    "0": 506,
    "3": 2296
  },
  "48": {
    "0": 516,
    "1": 2098
  },
  "49": {
    "0": 538,
    "2": 1836
  },
  "50": {
    "0": 488,
    "1": 2654
  },
  "51": {
    "0": 534,
    "2": 3010
  },
  "52": {
    "0": 498,
    "1": 1084
  },
  "53": {
    "0": 532,
    "3": 4288
  },
  "54": {
    "0": 516,
    "2": 2692
  },
  "55": {
    "0": 570,
    "4": 5444
  },
  "56": {
    "0": 726,
    "2": 1358
  },
  "57": {
    "0": 556,
    "4": 1260
  },
  "58": {
    "0": 516,
    "4": 2162
  },
  "59": {
    "0": 536,
    "3": 1258
  },
  "60": {
    "0": 528,
    "1": 2012
  },
  "61": {
    "0": 560,
    "1": 2160
  },
  "62": {
    "0": 554,
    "4": 3928
  },
  "63": {
    "0": 512,
    "2": 2062
  },
  "64": {
    "0": 498,
    "1": 3246
  },
  "65": {
    "0": 520,
    "3": 1710
  },
  "66": {
    "0": 494,
    "3": 3060
  },
  "67": {
    "0": 548,
    "4": 1436
  },
  "68": {
    "0": 514,
    "3": 3344
  },
  "69": {
    "0": 520,
    "3": 1930
  },
  "70": {
    "0": 516,
    "3": 1608
  },
  "71": {
    "0": 508,
    "1": 1664
  },
  "72": {
    "0": 520,
    "0": 4600
  },
  "73": {
    "0": 294,
    "6": 3332
  },
  "74": {
    "0": 560,
    "5": 3784
  },
  "75": {
    "0": 716,
    "2": 4308
  },
  "76": {
    "0": 508,
    "1": 2024
  },
  "77": {
    "0": 614,
    "1": 2096
  },
  "78": {
    "0": 536,
    "3": 1624
  },
  "79": {
    "0": 564,
    "0": 4778
  },
  "80": {
    "0": 266,
    "3": 1088
  },
  "81": {
    "0": 676,
    "2": 1340
  },
  "82": {
    "0": 672,
    "6": 2016
  },
  "83": {
    "0": 526,
    "4": 1428
  },
  "84": {
    "0": 704,
    "3": 4644
  },
  "85": {
    "0": 534,
    "6": 1532
  },
  "86": {
    "0": 602,
    "7": 2822
  },
  "87": {
    "0": 550,
    "2": 3184
  },
  "88": {
    "0": 624,
    "7": 2030
  },
  "89": {
    "0": 526,
    "2": 1248
  },
  "90": {
    "0": 512,
    "6": 1846
  },
  "91": {
    "0": 544,
    "2": 3504
  },
  "92": {
    "0": 516,
    "1": 3398
  },
  "93": {
    "0": 538,
    "6": 3034
  },
  "94": {
    "0": 566,
    "6": 1630
  },
  "95": {
    "0": 530,
    "1": 1674
  },
  "96": {
    "0": 534,
    "7": 1346
  },
  "97": {
    "0": 544,
    "1": 1248
  },
  "98": {
    "0": 544,
    "4": 2630
  },
  "99": {
    "0": 514,
    "1": 2578
  }
}
